data_structures/__init__.py
data_structures/array_.py
data_structures/graph.py
data_structures/linked_list.py
data_structures/my_queue.py
data_structures/stack.py
data_structures/tree.py
basic_python_data_structures_for_bootcamp-0.1.0.dist-info/LICENSE
basic_python_data_structures_for_bootcamp-0.1.0.dist-info/METADATA
basic_python_data_structures_for_bootcamp-0.1.0.dist-info/WHEEL
basic_python_data_structures_for_bootcamp-0.1.0.dist-info/top_level.txt
basic_python_data_structures_for_bootcamp-0.1.0.dist-info/RECORD
